bellman_filter_dfsv/__init__.py
bellman_filter_dfsv/_bellman_math.py
bellman_filter_dfsv/_particle_math.py
bellman_filter_dfsv/estimation.py
bellman_filter_dfsv/filters.py
bellman_filter_dfsv/simulation.py
bellman_filter_dfsv/smoothing.py
bellman_filter_dfsv/types.py
bellman_filter_dfsv/utils/__init__.py
bellman_filter_dfsv/utils/analysis.py
bellman_filter_dfsv/utils/jax_helpers.py
bellman_filter_dfsv-2.0.0.dist-info/licenses/LICENSE
bellman_filter_dfsv-2.0.0.dist-info/METADATA
bellman_filter_dfsv-2.0.0.dist-info/WHEEL
bellman_filter_dfsv-2.0.0.dist-info/top_level.txt
bellman_filter_dfsv-2.0.0.dist-info/RECORD
