Metadata-Version: 2.4
Name: bellman-filter-dfsv
Version: 2.0.0
Summary: High-performance JAX-based filtering for Dynamic Factor Stochastic Volatility (DFSV) models with functional architecture
Author-email: Givani Boekestijn <givaniboek@hotmail.com>
Keywords: jax,filtering,stochastic-volatility,dynamic-factors,econometrics,finance,equinox
Classifier: Development Status :: 4 - Beta
Classifier: Intended Audience :: Science/Research
Classifier: License :: OSI Approved :: MIT License
Classifier: Programming Language :: Python :: 3
Classifier: Programming Language :: Python :: 3.11
Classifier: Programming Language :: Python :: 3.12
Classifier: Programming Language :: Python :: 3.13
Classifier: Topic :: Scientific/Engineering
Classifier: Topic :: Scientific/Engineering :: Mathematics
Classifier: Topic :: Office/Business :: Financial
Requires-Python: >=3.11
License-File: LICENSE
Requires-Dist: jax>=0.4.35
Requires-Dist: jaxlib>=0.4.35
Requires-Dist: jaxtyping>=0.2.34
Requires-Dist: equinox>=0.11.8
Requires-Dist: optimistix>=0.0.10
Requires-Dist: optax>=0.2.4
Requires-Dist: numpy>=1.26.0
Requires-Dist: scipy>=1.14.0
Provides-Extra: dev
Requires-Dist: pytest>=8.3.5; extra == "dev"
Requires-Dist: pytest-cov>=6.1.1; extra == "dev"
Requires-Dist: hypothesis>=6.92.0; extra == "dev"
Requires-Dist: ruff>=0.8.0; extra == "dev"
Requires-Dist: basedpyright>=1.23.0; extra == "dev"
Provides-Extra: docs
Requires-Dist: sphinx>=8.2.3; extra == "docs"
Requires-Dist: sphinx-rtd-theme>=3.0.2; extra == "docs"
Provides-Extra: examples
Requires-Dist: matplotlib>=3.8.0; extra == "examples"
Requires-Dist: seaborn>=0.13.2; extra == "examples"
Requires-Dist: pandas>=2.1.0; extra == "examples"
Requires-Dist: yfinance>=0.2.0; extra == "examples"
Provides-Extra: all
Requires-Dist: bellman-filter-dfsv[dev,docs,examples]; extra == "all"
Dynamic: license-file
